velog_sync.py
velog_sync-0.2.0.dist-info/licenses/LICENSE
velog_sync-0.2.0.dist-info/METADATA
velog_sync-0.2.0.dist-info/WHEEL
velog_sync-0.2.0.dist-info/entry_points.txt
velog_sync-0.2.0.dist-info/top_level.txt
velog_sync-0.2.0.dist-info/RECORD
