Metadata-Version: 2.4
Name: velog_sync
Version: 0.2.0
Summary: Velog 글을 Markdown으로 백업 (시리즈별 폴더) — velog_sync PyPI 패키지 실행
Author-email: choi-hyk <blindlchoil@gmail.com>
License: MIT License
Classifier: License :: OSI Approved :: MIT License
Requires-Python: >=3.10
License-File: LICENSE
Requires-Dist: requests>=2.32.0
Requires-Dist: tzdata>=2024.1
Dynamic: license-file
